{"config": {"view": {"continuousWidth": 300, "continuousHeight": 300}, "locale": {"number": {"decimal": ",", "thousands": ".", "grouping": [3], "currency": ["", "\u00a0\u20ac"]}}, "title": {"dx": 30, "dy": -15, "fontSize": 15}}, "vconcat": [{"facet": {"column": {"field": "seg", "header": {"labelFontSize": 15}, "sort": {"field": "order"}, "title": null, "type": "nominal"}, "row": {"field": "type", "header": {"labelFontSize": 15}, "sort": {"field": "order"}, "title": null, "type": "nominal"}}, "spec": {"layer": [{"mark": {"type": "rule"}, "encoding": {"y": {"aggregate": "mean", "field": "zero", "type": "quantitative"}}, "transform": [{"calculate": "0", "as": "zero"}]}, {"mark": {"type": "errorbar", "ticks": {"width": 10}}, "encoding": {"color": {"field": "type", "legend": null, "scale": {"range": ["DarkViolet", "DarkMagenta"]}, "sort": {"field": "order"}, "title": null, "type": "nominal"}, "tooltip": {"value": null}, "x": {"axis": {"labelAngle": 0, "labelFontSize": 11}, "field": "M", "sort": {"field": "order"}, "title": null, "type": "nominal"}, "y": {"axis": {"labelFontSize": 11}, "field": "lower", "title": null, "type": "quantitative"}, "y2": {"field": "upper"}}}, {"mark": {"type": "line", "point": {"size": 50}}, "encoding": {"color": {"field": "type", "legend": null, "scale": {"range": ["DarkViolet", "DarkMagenta"]}, "sort": {"field": "order"}, "title": null, "type": "nominal"}, "tooltip": [{"field": "prop", "format": ".2f", "title": "Estimaci\u00f3n", "type": "quantitative"}, {"field": "lower", "format": ".2f", "title": "L\u00edmite inferior", "type": "quantitative"}, {"field": "upper", "format": ".2f", "title": "L\u00edmite superior", "type": "quantitative"}], "x": {"axis": {"labelAngle": 0, "labelFontSize": 11}, "field": "M", "sort": {"field": "order"}, "title": null, "type": "nominal"}, "y": {"axis": {"labelFontSize": 11}, "field": "prop", "title": null, "type": "quantitative"}}, "name": "view_2025"}], "height": 175, "width": {"step": 45, "for": "position"}}, "resolve": {"axis": {"x": "independent", "y": "independent"}}, "transform": [{"filter": "datum.type == 'Absoluta (puntos porcentuales)'"}]}, {"facet": {"column": {"field": "seg", "header": {"labelFontSize": 15}, "sort": {"field": "order"}, "title": null, "type": "nominal"}, "row": {"field": "type", "header": {"labelFontSize": 15}, "sort": {"field": "order"}, "title": null, "type": "nominal"}}, "spec": {"layer": [{"mark": {"type": "rule"}, "encoding": {"y": {"aggregate": "mean", "field": "zero", "type": "quantitative"}}, "transform": [{"calculate": "0", "as": "zero"}]}, {"mark": {"type": "errorbar", "ticks": {"width": 10}}, "encoding": {"color": {"field": "type", "legend": null, "scale": {"range": ["DarkViolet", "DarkMagenta"]}, "sort": {"field": "order"}, "title": null, "type": "nominal"}, "tooltip": {"value": null}, "x": {"axis": {"labelAngle": 0, "labelFontSize": 11}, "field": "M", "sort": {"field": "order"}, "title": null, "type": "nominal"}, "y": {"axis": {"labelFontSize": 11}, "field": "lower", "title": null, "type": "quantitative"}, "y2": {"field": "upper"}}}, {"mark": {"type": "line", "point": {"size": 50}}, "encoding": {"color": {"field": "type", "legend": null, "scale": {"range": ["DarkViolet", "DarkMagenta"]}, "sort": {"field": "order"}, "title": null, "type": "nominal"}, "tooltip": [{"field": "prop", "format": ".2f", "title": "Estimaci\u00f3n", "type": "quantitative"}, {"field": "lower", "format": ".2f", "title": "L\u00edmite inferior", "type": "quantitative"}, {"field": "upper", "format": ".2f", "title": "L\u00edmite superior", "type": "quantitative"}], "x": {"axis": {"labelAngle": 0, "labelFontSize": 11}, "field": "M", "sort": {"field": "order"}, "title": null, "type": "nominal"}, "y": {"axis": {"labelFontSize": 11}, "field": "prop", "title": null, "type": "quantitative"}}, "name": "view_2026"}], "height": 175, "width": {"step": 45, "for": "position"}}, "resolve": {"axis": {"x": "independent", "y": "independent"}}, "transform": [{"filter": "datum.type == 'Relativa (%)'"}]}], "data": {"name": "data-1f7db8ddb46d44da93f07a11870c25f7"}, "params": [{"name": "param_4299", "select": {"type": "interval", "encodings": ["x", "y"]}, "bind": "scales", "views": ["view_2025"]}, {"name": "param_4300", "select": {"type": "interval", "encodings": ["x", "y"]}, "bind": "scales", "views": ["view_2026"]}], "title": {"text": ["Brechas de g\u00e9nero de: Poblaci\u00f3n que ha consumido antidepresivos en las dos \u00faltimas semanas", "por nivel de h\u00e1bitat (puntos porcentuales / porcentajes e intervalos de confianza al 95%)"], "subtitle": "Fuente: Encuesta Andaluza de Salud (adultos). C\u00f3digo de variable: P16A07"}, "transform": [{"filter": "true == true"}], "$schema": "https://vega.github.io/schema/vega-lite/v5.17.0.json", "datasets": {"data-1f7db8ddb46d44da93f07a11870c25f7": [{"type": "Absoluta (puntos porcentuales)", "M": "2007", "seg": "<10.000 hab", "prop": 3.028156034374731, "lower": 1.0325921588546818, "upper": 5.220783461842796, "order": 0}, {"type": "Absoluta (puntos porcentuales)", "M": "2007", "seg": "10-50.000 hab", "prop": 4.17754299102056, "lower": 2.3146814074074666, "upper": 6.1018755459019145, "order": 1}, {"type": "Absoluta (puntos porcentuales)", "M": "2007", "seg": ">50.000 hab", "prop": 4.3192489491117225, "lower": 2.216976064494061, "upper": 6.422780197221234, "order": 2}, {"type": "Absoluta (puntos porcentuales)", "M": "2007", "seg": "Capitales", "prop": 5.337472511729051, "lower": 3.698268322234663, "upper": 7.254297824299546, "order": 3}, {"type": "Absoluta (puntos porcentuales)", "M": "2007", "seg": "Total", "prop": 4.316476269857024, "lower": 3.3192402789323094, "upper": 5.335009386424128, "order": 4}, {"type": "Absoluta (puntos porcentuales)", "M": "2012", "seg": "<10.000 hab", "prop": 7.23038617240106, "lower": 4.980655953297488, "upper": 10.132688292611455, "order": 5}, {"type": "Absoluta (puntos porcentuales)", "M": "2012", "seg": "10-50.000 hab", "prop": 4.5578663480510695, "lower": 2.347176898980688, "upper": 6.66556105095837, "order": 6}, {"type": "Absoluta (puntos porcentuales)", "M": "2012", "seg": ">50.000 hab", "prop": 5.023691312677183, "lower": 2.705744198696141, "upper": 7.175884201108783, "order": 7}, {"type": "Absoluta (puntos porcentuales)", "M": "2012", "seg": "Capitales", "prop": 4.572109950153172, "lower": 2.276877698619703, "upper": 6.623740900875109, "order": 8}, {"type": "Absoluta (puntos porcentuales)", "M": "2012", "seg": "Total", "prop": 5.207880493103151, "lower": 4.019558069321505, "upper": 6.2604377922146455, "order": 9}, {"type": "Absoluta (puntos porcentuales)", "M": "2016", "seg": "<10.000 hab", "prop": 6.586893176538064, "lower": 4.364402184364255, "upper": 9.144673736607487, "order": 10}, {"type": "Absoluta (puntos porcentuales)", "M": "2016", "seg": "10-50.000 hab", "prop": 5.562428809747426, "lower": 3.7720360977475416, "upper": 7.410078336472228, "order": 11}, {"type": "Absoluta (puntos porcentuales)", "M": "2016", "seg": ">50.000 hab", "prop": 3.384365173540435, "lower": 1.447251168564049, "upper": 5.532947682925276, "order": 12}, {"type": "Absoluta (puntos porcentuales)", "M": "2016", "seg": "Capitales", "prop": 4.2654315629091535, "lower": 2.3927972225063177, "upper": 6.240801986450769, "order": 13}, {"type": "Absoluta (puntos porcentuales)", "M": "2016", "seg": "Total", "prop": 4.914627284746832, "lower": 3.9339660669359984, "upper": 5.9378302843121995, "order": 14}, {"type": "Absoluta (puntos porcentuales)", "M": "2023", "seg": "<10.000 hab", "prop": 1.8927463569563958, "lower": -0.31191051710487167, "upper": 4.161485269841489, "order": 15}, {"type": "Absoluta (puntos porcentuales)", "M": "2023", "seg": "10-50.000 hab", "prop": 4.476487103115182, "lower": 2.8689327659332173, "upper": 6.289658525280189, "order": 16}, {"type": "Absoluta (puntos porcentuales)", "M": "2023", "seg": ">50.000 hab", "prop": 3.242063488544683, "lower": -0.8462934173257582, "upper": 5.801489859066105, "order": 17}, {"type": "Absoluta (puntos porcentuales)", "M": "2023", "seg": "Capitales", "prop": 4.9408240409024575, "lower": 2.8733535550342344, "upper": 6.805349148119776, "order": 18}, {"type": "Absoluta (puntos porcentuales)", "M": "2023", "seg": "Total", "prop": 3.936816857186496, "lower": 2.3648407683268515, "upper": 5.036551584985014, "order": 19}, {"type": "Relativa (%)", "M": "2007", "seg": "<10.000 hab", "prop": 98.77230439186776, "lower": 24.319580782018033, "upper": 237.43983118079507, "order": 20}, {"type": "Relativa (%)", "M": "2007", "seg": "10-50.000 hab", "prop": 179.90469701877652, "lower": 70.14411192336036, "upper": 388.01479589155485, "order": 21}, {"type": "Relativa (%)", "M": "2007", "seg": ">50.000 hab", "prop": 302.60152077710796, "lower": 106.22407372278366, "upper": 773.9872095318442, "order": 22}, {"type": "Relativa (%)", "M": "2007", "seg": "Capitales", "prop": 298.72106954474486, "lower": 143.6869692884612, "upper": 597.1330440755817, "order": 23}, {"type": "Relativa (%)", "M": "2007", "seg": "Total", "prop": 201.69414593419347, "lower": 130.74634886984458, "upper": 301.92950458410064, "order": 24}, {"type": "Relativa (%)", "M": "2012", "seg": "<10.000 hab", "prop": 282.72437045194414, "lower": 136.91075195357593, "upper": 570.6319451781169, "order": 25}, {"type": "Relativa (%)", "M": "2012", "seg": "10-50.000 hab", "prop": 128.06375279100604, "lower": 51.328868050104035, "upper": 243.35348573432407, "order": 26}, {"type": "Relativa (%)", "M": "2012", "seg": ">50.000 hab", "prop": 234.03530074049127, "lower": 78.44160947580536, "upper": 598.3749711821309, "order": 27}, {"type": "Relativa (%)", "M": "2012", "seg": "Capitales", "prop": 115.19703277704893, "lower": 41.524028958254725, "upper": 216.8669960812197, "order": 28}, {"type": "Relativa (%)", "M": "2012", "seg": "Total", "prop": 165.0832490636536, "lower": 107.29921995427397, "upper": 230.64265747810126, "order": 29}, {"type": "Relativa (%)", "M": "2016", "seg": "<10.000 hab", "prop": 354.5103803419519, "lower": 156.07454091600493, "upper": 774.8663529994891, "order": 30}, {"type": "Relativa (%)", "M": "2016", "seg": "10-50.000 hab", "prop": 323.2726017107262, "lower": 155.00239566587072, "upper": 659.5829498532269, "order": 31}, {"type": "Relativa (%)", "M": "2016", "seg": ">50.000 hab", "prop": 164.7688187169741, "lower": 43.79012105199977, "upper": 401.56757162238534, "order": 32}, {"type": "Relativa (%)", "M": "2016", "seg": "Capitales", "prop": 140.4431298243716, "lower": 56.074835410251445, "upper": 280.3060971345022, "order": 33}, {"type": "Relativa (%)", "M": "2016", "seg": "Total", "prop": 224.8035216418143, "lower": 155.2931913346602, "upper": 331.8000918776899, "order": 34}, {"type": "Relativa (%)", "M": "2023", "seg": "<10.000 hab", "prop": 39.25004003956198, "lower": -5.762207832016612, "upper": 117.95561052800807, "order": 35}, {"type": "Relativa (%)", "M": "2023", "seg": "10-50.000 hab", "prop": 216.8757014021911, "lower": 92.2602697165022, "upper": 550.086560299705, "order": 36}, {"type": "Relativa (%)", "M": "2023", "seg": ">50.000 hab", "prop": 97.57080417176277, "lower": -10.573423718259328, "upper": 221.7558034281324, "order": 37}, {"type": "Relativa (%)", "M": "2023", "seg": "Capitales", "prop": 138.20558267119847, "lower": 62.28240418674791, "upper": 247.11414195527874, "order": 38}, {"type": "Relativa (%)", "M": "2023", "seg": "Total", "prop": 121.82547962983432, "lower": 65.87205213297096, "upper": 187.79468019588217, "order": 39}]}}