{"config": {"view": {"continuousWidth": 300, "continuousHeight": 300}, "locale": {"number": {"decimal": ",", "thousands": ".", "grouping": [3], "currency": ["", "\u00a0\u20ac"]}}, "title": {"dx": 30, "dy": -15, "fontSize": 15}}, "data": {"name": "data-0a3231122c41398594c310378b05e7da"}, "facet": {"column": {"field": "seg2", "header": {"labelFontSize": 15}, "sort": {"field": "order"}, "title": null, "type": "nominal"}, "row": {"field": "row", "header": {"labels": false}, "sort": {"field": "order"}, "title": null, "type": "nominal"}}, "spec": {"layer": [{"mark": {"type": "errorbar", "ticks": {"width": 10}}, "encoding": {"tooltip": {"value": null}, "y": {"axis": {"format": "%", "labelFontSize": 11}, "field": "lower", "title": null, "type": "quantitative"}, "y2": {"field": "upper"}}}, {"mark": {"type": "line", "point": {"size": 50}}, "encoding": {"tooltip": [{"field": "seg1", "title": "Grupo", "type": "nominal"}, {"field": "prop", "format": ".2%", "title": "Estimaci\u00f3n", "type": "quantitative"}, {"field": "lower", "format": ".2%", "title": "L\u00edmite inferior", "type": "quantitative"}, {"field": "upper", "format": ".2%", "title": "L\u00edmite superior", "type": "quantitative"}], "y": {"axis": {"format": "%", "labelFontSize": 11}, "field": "prop", "title": null, "type": "quantitative"}}, "name": "view_469"}], "encoding": {"color": {"field": "seg1", "legend": {"labelFontSize": 12, "symbolSize": 400}, "sort": {"field": "order"}, "title": null, "type": "nominal"}, "x": {"axis": {"labelAngle": 0, "labelFontSize": 11}, "field": "M", "sort": {"field": "order"}, "title": null, "type": "nominal"}, "xOffset": {"field": "seg1", "scale": {"paddingOuter": 0.5}, "sort": {"field": "order"}, "type": "nominal"}}, "height": 175, "width": {"step": 45, "for": "position"}}, "params": [{"name": "param_2251", "select": {"type": "interval", "encodings": ["x", "y"]}, "bind": "scales", "views": ["view_469"]}], "resolve": {"axis": {"x": "independent", "y": "independent"}, "scale": {"xOffset": "independent"}}, "title": {"text": ["Hogares con calidad medioambiental mala o muy mala en la zona de residencia en cada", "edici\u00f3n seg\u00fan sexo y nivel de h\u00e1bitat (porcentajes e intervalos de confianza al 95%)"], "subtitle": "Fuente: Encuesta Andaluza de Salud (adultos). C\u00f3digo de variable: P5B_R"}, "transform": [{"calculate": "datum.seg1 == 'Total'", "as": "row"}, {"filter": "indexof(datum.M, '2') != -1"}], "$schema": "https://vega.github.io/schema/vega-lite/v5.16.3.json", "datasets": {"data-0a3231122c41398594c310378b05e7da": [{"M": "2007", "seg1": "Hombre", "seg2": "Menos de 2", "prop": 0.008775082882442007, "lower": 0.0, "upper": 0.038017682991772925, "order": 0}, {"M": "2007", "seg1": "Hombre", "seg2": "2/10", "prop": 0.022744171963986173, "lower": 0.013051748477475724, "upper": 0.0378085522167204, "order": 1}, {"M": "2007", "seg1": "Hombre", "seg2": "10/50", "prop": 0.023427109873375884, "lower": 0.0156850129240888, "upper": 0.036200016043249975, "order": 2}, {"M": "2007", "seg1": "Hombre", "seg2": "mas de 50", "prop": 0.02404956912616221, "lower": 0.013341737872955865, "upper": 0.04056186754222011, "order": 3}, {"M": "2007", "seg1": "Hombre", "seg2": "Capitales", "prop": 0.04616955990516644, "lower": 0.033206728394806914, "upper": 0.06157632139043978, "order": 4}, {"M": "2007", "seg1": "Hombre", "seg2": "Total", "prop": 0.029445223771672767, "lower": 0.024210072038877564, "upper": 0.03641294833885247, "order": 5}, {"M": "2007", "seg1": "Mujer", "seg2": "Menos de 2", "prop": 0.014593975218540563, "lower": 0.0, "upper": 0.05090915433453854, "order": 6}, {"M": "2007", "seg1": "Mujer", "seg2": "2/10", "prop": 0.03222005652510596, "lower": 0.019770433196608275, "upper": 0.04834348131907699, "order": 7}, {"M": "2007", "seg1": "Mujer", "seg2": "10/50", "prop": 0.044195248583116235, "lower": 0.03276501531722033, "upper": 0.058956543139255684, "order": 8}, {"M": "2007", "seg1": "Mujer", "seg2": "mas de 50", "prop": 0.039136716360968514, "lower": 0.026381707887569973, "upper": 0.05621024006886092, "order": 9}, {"M": "2007", "seg1": "Mujer", "seg2": "Capitales", "prop": 0.06605026701124242, "lower": 0.05256369254601009, "upper": 0.08379505721908743, "order": 10}, {"M": "2007", "seg1": "Mujer", "seg2": "Total", "prop": 0.04686257438403699, "lower": 0.03997900846811611, "upper": 0.05426931047965895, "order": 11}, {"M": "2007", "seg1": "Total", "seg2": "Menos de 2", "prop": 0.011651329310782738, "lower": 0.0034192675899177845, "upper": 0.03323041179078979, "order": 12}, {"M": "2007", "seg1": "Total", "seg2": "2/10", "prop": 0.02747343409284341, "lower": 0.01916248556312043, "upper": 0.038996910587520264, "order": 13}, {"M": "2007", "seg1": "Total", "seg2": "10/50", "prop": 0.03383793369552025, "lower": 0.026085746630626565, "upper": 0.04314895154570494, "order": 14}, {"M": "2007", "seg1": "Total", "seg2": "mas de 50", "prop": 0.03162266764550997, "lower": 0.02312094156202786, "upper": 0.04258102320830042, "order": 15}, {"M": "2007", "seg1": "Total", "seg2": "Capitales", "prop": 0.05661035675974902, "lower": 0.04604410296104959, "upper": 0.06716945560261589, "order": 16}, {"M": "2007", "seg1": "Total", "seg2": "Total", "prop": 0.03829160054035863, "lower": 0.03384016406364746, "upper": 0.04346016656323603, "order": 17}, {"M": "2012", "seg1": "Hombre", "seg2": "Menos de 2", "prop": 0.006278371344640823, "lower": 0.0, "upper": 0.035535584661469784, "order": 18}, {"M": "2012", "seg1": "Hombre", "seg2": "2/10", "prop": 0.0017074007175221953, "lower": 0.0, "upper": 0.010287268532890298, "order": 19}, {"M": "2012", "seg1": "Hombre", "seg2": "10/50", "prop": 0.016224422610274635, "lower": 0.009228502530931798, "upper": 0.026397369050590414, "order": 20}, {"M": "2012", "seg1": "Hombre", "seg2": "mas de 50", "prop": 0.020723800281013536, "lower": 0.0121490772563071, "upper": 0.03770559312100402, "order": 21}, {"M": "2012", "seg1": "Hombre", "seg2": "Capitales", "prop": 0.024179463974696475, "lower": 0.014775737057130645, "upper": 0.03685385027608482, "order": 22}, {"M": "2012", "seg1": "Hombre", "seg2": "Total", "prop": 0.016571726083400858, "lower": 0.012334073217998918, "upper": 0.021176937123822098, "order": 23}, {"M": "2012", "seg1": "Mujer", "seg2": "Menos de 2", "prop": 0.0, "lower": 0.0, "upper": 0.019359416705111314, "order": 24}, {"M": "2012", "seg1": "Mujer", "seg2": "2/10", "prop": 0.004914258437121765, "lower": 0.0016002789025885904, "upper": 0.013735192194872113, "order": 25}, {"M": "2012", "seg1": "Mujer", "seg2": "10/50", "prop": 0.025586766025423747, "lower": 0.017078995494513884, "upper": 0.03711169233486957, "order": 26}, {"M": "2012", "seg1": "Mujer", "seg2": "mas de 50", "prop": 0.010910850516986249, "lower": 0.005178635152168162, "upper": 0.021046967850707907, "order": 27}, {"M": "2012", "seg1": "Mujer", "seg2": "Capitales", "prop": 0.019245760245238493, "lower": 0.011262442843307338, "upper": 0.028544641923638703, "order": 28}, {"M": "2012", "seg1": "Mujer", "seg2": "Total", "prop": 0.016296712869771655, "lower": 0.012182836750875219, "upper": 0.02106936272063557, "order": 29}, {"M": "2012", "seg1": "Total", "seg2": "Menos de 2", "prop": 0.0032083451876103973, "lower": 0.0, "upper": 0.01609839666805027, "order": 30}, {"M": "2012", "seg1": "Total", "seg2": "2/10", "prop": 0.0033059004708390002, "lower": 0.0008476102404697502, "upper": 0.00828610583892284, "order": 31}, {"M": "2012", "seg1": "Total", "seg2": "10/50", "prop": 0.020937508637651175, "lower": 0.015357094775830055, "upper": 0.028770472554121178, "order": 32}, {"M": "2012", "seg1": "Total", "seg2": "mas de 50", "prop": 0.015761777532203945, "lower": 0.010228687695477516, "upper": 0.024017169872114153, "order": 33}, {"M": "2012", "seg1": "Total", "seg2": "Capitales", "prop": 0.02158051788966518, "lower": 0.015165791882760465, "upper": 0.02883405728360531, "order": 34}, {"M": "2012", "seg1": "Total", "seg2": "Total", "prop": 0.01643167304727566, "lower": 0.013544412558954215, "upper": 0.02033109338633326, "order": 35}, {"M": "2015", "seg1": "Hombre", "seg2": "Menos de 2", "prop": 0.007247381496158259, "lower": 0.0, "upper": 0.037225193457936324, "order": 36}, {"M": "2015", "seg1": "Hombre", "seg2": "2/10", "prop": 0.014451947682153991, "lower": 0.005548402991854553, "upper": 0.029281935851334193, "order": 37}, {"M": "2015", "seg1": "Hombre", "seg2": "10/50", "prop": 0.01184318423967012, "lower": 0.006024554169281088, "upper": 0.02107897024159979, "order": 38}, {"M": "2015", "seg1": "Hombre", "seg2": "mas de 50", "prop": 0.016120850107447543, "lower": 0.008261836602313116, "upper": 0.027263641822854488, "order": 39}, {"M": "2015", "seg1": "Hombre", "seg2": "Capitales", "prop": 0.013736874089593313, "lower": 0.007576897037222774, "upper": 0.02417729412711757, "order": 40}, {"M": "2015", "seg1": "Hombre", "seg2": "Total", "prop": 0.013593903521397138, "lower": 0.00976951413748203, "upper": 0.018103850392683984, "order": 41}, {"M": "2015", "seg1": "Mujer", "seg2": "Menos de 2", "prop": 0.0, "lower": 0.0, "upper": 0.01652757142675041, "order": 42}, {"M": "2015", "seg1": "Mujer", "seg2": "2/10", "prop": 0.005681191727079944, "lower": 0.0016161356113369976, "upper": 0.015847094606386048, "order": 43}, {"M": "2015", "seg1": "Mujer", "seg2": "10/50", "prop": 0.017038534432155708, "lower": 0.009750836748754496, "upper": 0.025782296508052204, "order": 44}, {"M": "2015", "seg1": "Mujer", "seg2": "mas de 50", "prop": 0.033476934411835614, "lower": 0.022029227717009846, "upper": 0.050007369386749476, "order": 45}, {"M": "2015", "seg1": "Mujer", "seg2": "Capitales", "prop": 0.027346696425363772, "lower": 0.017950803018420117, "upper": 0.03807995547762574, "order": 46}, {"M": "2015", "seg1": "Mujer", "seg2": "Total", "prop": 0.021369694793157056, "lower": 0.016665129310828596, "upper": 0.02678450038231162, "order": 47}, {"M": "2015", "seg1": "Total", "seg2": "Menos de 2", "prop": 0.003673907264063683, "lower": 0.0, "upper": 0.01869750753427594, "order": 48}, {"M": "2015", "seg1": "Total", "seg2": "2/10", "prop": 0.010063301890099796, "lower": 0.005378294640136854, "upper": 0.018880569024049484, "order": 49}, {"M": "2015", "seg1": "Total", "seg2": "10/50", "prop": 0.01446428363460782, "lower": 0.009417840253998864, "upper": 0.02134001564747282, "order": 50}, {"M": "2015", "seg1": "Total", "seg2": "mas de 50", "prop": 0.024935666386818964, "lower": 0.017811017244764873, "upper": 0.03405403968312066, "order": 51}, {"M": "2015", "seg1": "Total", "seg2": "Capitales", "prop": 0.020902385572242714, "lower": 0.014609762670254442, "upper": 0.028504041599396176, "order": 52}, {"M": "2015", "seg1": "Total", "seg2": "Total", "prop": 0.017563242265739496, "lower": 0.014519967751043483, "upper": 0.021304608932534143, "order": 53}, {"M": "2023", "seg1": "Hombre", "seg2": "Menos de 2", "prop": 0.0, "lower": 0.0, "upper": 0.01611166795448482, "order": 54}, {"M": "2023", "seg1": "Hombre", "seg2": "2/10", "prop": 0.002713737119373586, "lower": 0.0, "upper": 0.009723702399700778, "order": 55}, {"M": "2023", "seg1": "Hombre", "seg2": "10/50", "prop": 0.0046691389163865185, "lower": 0.0013702700774969555, "upper": 0.011676193518446565, "order": 56}, {"M": "2023", "seg1": "Hombre", "seg2": "mas de 50", "prop": 0.005624444117585148, "lower": 0.0013638082647663044, "upper": 0.015618048774450983, "order": 57}, {"M": "2023", "seg1": "Hombre", "seg2": "Capitales", "prop": 0.029003568777223526, "lower": 0.019037086078128904, "upper": 0.04162772975319884, "order": 58}, {"M": "2023", "seg1": "Hombre", "seg2": "Total", "prop": 0.011361681073861112, "lower": 0.008275758794728158, "upper": 0.016081053052015504, "order": 59}, {"M": "2023", "seg1": "Mujer", "seg2": "Menos de 2", "prop": 0.0, "lower": 0.0, "upper": 0.00786501084104086, "order": 60}, {"M": "2023", "seg1": "Mujer", "seg2": "2/10", "prop": 0.0034245346477205217, "lower": 0.0012438158312852185, "upper": 0.008214928321311444, "order": 61}, {"M": "2023", "seg1": "Mujer", "seg2": "10/50", "prop": 0.006705202322175191, "lower": 0.0032150222331711895, "upper": 0.01204823093285553, "order": 62}, {"M": "2023", "seg1": "Mujer", "seg2": "mas de 50", "prop": 0.0035006993549384995, "lower": 0.0012769005091282238, "upper": 0.009299347095035052, "order": 63}, {"M": "2023", "seg1": "Mujer", "seg2": "Capitales", "prop": 0.03247385875820176, "lower": 0.023278814065313434, "upper": 0.04183978746423445, "order": 64}, {"M": "2023", "seg1": "Mujer", "seg2": "Total", "prop": 0.01291108157974469, "lower": 0.009752518358108227, "upper": 0.016558613138267102, "order": 65}, {"M": "2023", "seg1": "Total", "seg2": "Menos de 2", "prop": 0.0, "lower": 0.0, "upper": 0.005302785449010288, "order": 66}, {"M": "2023", "seg1": "Total", "seg2": "2/10", "prop": 0.003090663761901724, "lower": 0.0012504949339494239, "upper": 0.006844574668296665, "order": 67}, {"M": "2023", "seg1": "Total", "seg2": "10/50", "prop": 0.005698067143367614, "lower": 0.0034753798566348054, "upper": 0.009969784689776209, "order": 68}, {"M": "2023", "seg1": "Total", "seg2": "mas de 50", "prop": 0.004465563092031441, "lower": 0.002040007782045429, "upper": 0.009592723067129258, "order": 69}, {"M": "2023", "seg1": "Total", "seg2": "Capitales", "prop": 0.03088575471580346, "lower": 0.02403768746174622, "upper": 0.03985554569140751, "order": 70}, {"M": "2023", "seg1": "Total", "seg2": "Total", "prop": 0.012184429721222308, "lower": 0.009721522797996596, "upper": 0.014834181348257763, "order": 71}]}}